pdemtools/__init__.py
pdemtools/_accessor.py
pdemtools/_coreg.py
pdemtools/_geomorphometry.py
pdemtools/_index_search.py
pdemtools/_utils.py
pdemtools/data.py
pdemtools/load.py
pdemtools/mosaic_index/ArcticDEM_Mosaic_Index_v3_gpkg.gpkg
pdemtools/mosaic_index/ArcticDEM_Mosaic_Index_v4_1_gpkg.gpkg
pdemtools/mosaic_index/REMA_Mosaic_Index_v2_gpkg.gpkg
pdemtools/test_data/test_arcticdem_index_kiv_steenstrup.parquet
pdemtools-1.2.1.dist-info/licenses/LICENSE.md
pdemtools-1.2.1.dist-info/METADATA
pdemtools-1.2.1.dist-info/WHEEL
pdemtools-1.2.1.dist-info/top_level.txt
pdemtools-1.2.1.dist-info/RECORD
