Metadata-Version: 2.4
Name: pdemtools
Version: 1.2.1
Summary: Conveniently search, download, and preprocess ArcticDEM and REMA products.
Author-email: Tom Chudley <thomas.r.chudley@durham.ac.uk>
License: MIT
Project-URL: Homepage, https://github.com/trchudley/pdemtools
Project-URL: Documentation, https://pdemtools.readthedocs.io/
Project-URL: Repository, https://github.com/trchudley/pdemtools
Project-URL: Issues, https://github.com/trchudley/pdemtools/issues
Keywords: geospatial,elevation,arcticdem,rema,dem
Classifier: Intended Audience :: Science/Research
Classifier: Programming Language :: Python :: 3
Classifier: License :: OSI Approved :: MIT License
Classifier: Operating System :: OS Independent
Classifier: Topic :: Scientific/Engineering
Classifier: Topic :: Scientific/Engineering :: GIS
Classifier: Topic :: Scientific/Engineering :: Image Processing
Requires-Python: >=3.10
License-File: LICENSE.md
Requires-Dist: rioxarray
Requires-Dist: rasterio
Requires-Dist: geopandas
Requires-Dist: pandas
Requires-Dist: shapely
Requires-Dist: numpy
Requires-Dist: GDAL
Requires-Dist: opencv-python
Requires-Dist: scipy
Requires-Dist: numba
Requires-Dist: pyarrow
Requires-Dist: fiona
Dynamic: license-file
